{"pageProps":{"elements":[{"href":"https://docs.velas.com/cli/usage#velas-create-stake-account","name":"create-stake-account","description":"","icon":{"src":"/_next/static/media/velas.ebad41bb.ico","height":16,"width":16,"blurWidth":0,"blurHeight":0},"pattern":{"y":16,"squares":[[0,1],[1,3]]}},{"href":"https://docs.velas.com/cli/usage#velas-deactivate-stake","name":"deactivate-stake","description":"","icon":{"src":"/_next/static/media/velas.ebad41bb.ico","height":16,"width":16,"blurWidth":0,"blurHeight":0},"pattern":{"y":16,"squares":[[0,1],[1,3]]}},{"href":"https://docs.velas.com/cli/usage#velas-delegate-stake","name":"delegate-stake","description":"","icon":{"src":"/_next/static/media/velas.ebad41bb.ico","height":16,"width":16,"blurWidth":0,"blurHeight":0},"pattern":{"y":16,"squares":[[0,1],[1,3]]}},{"href":"https://docs.velas.com/cli/usage#velas-split-stake","name":"split-stake","description":"","icon":{"src":"/_next/static/media/velas.ebad41bb.ico","height":16,"width":16,"blurWidth":0,"blurHeight":0},"pattern":{"y":16,"squares":[[0,1],[1,3]]}},{"href":"https://docs.velas.com/cli/usage#velas-stake-authorize","name":"stake-authorize","description":"","icon":{"src":"/_next/static/media/velas.ebad41bb.ico","height":16,"width":16,"blurWidth":0,"blurHeight":0},"pattern":{"y":16,"squares":[[0,1],[1,3]]}},{"href":"https://docs.velas.com/cli/usage#velas-stake-set-lockup","name":"stake-set-lockup","description":"","icon":{"src":"/_next/static/media/velas.ebad41bb.ico","height":16,"width":16,"blurWidth":0,"blurHeight":0},"pattern":{"y":16,"squares":[[0,1],[1,3]]}},{"href":"https://docs.velas.com/cli/usage#velas-transfer","name":"transfer","description":"","icon":{"src":"/_next/static/media/velas.ebad41bb.ico","height":16,"width":16,"blurWidth":0,"blurHeight":0},"pattern":{"y":16,"squares":[[0,1],[1,3]]}},{"href":"https://docs.velas.com/cli/usage#velas-withdraw-stake","name":"withdraw-stake","description":"","icon":{"src":"/_next/static/media/velas.ebad41bb.ico","height":16,"width":16,"blurWidth":0,"blurHeight":0},"pattern":{"y":16,"squares":[[0,1],[1,3]]}}],"logoVelas":{"src":"/_next/static/media/velas.ebad41bb.ico","height":16,"width":16,"blurWidth":0,"blurHeight":0},"sections":[{"title":"Command-line Guide","id":"command_line_guide"},{"title":"Install the Exzo Network Tool Suite","id":"exzo_tool_suite"},{"title":"Using Exzo Network CLI","id":"exzo_network_cli"},{"title":"Connecting to a Cluster","id":"connecting_cluster"},{"title":"Send and Receive Tokens","id":"receive_tokens"},{"title":"Delegate Stake","id":"delegate_stake"},{"title":"Manage Stake Accounts","id":"stake_accounts"},{"title":"Deploy a Program","id":"deploy_program"},{"title":"Offline Transaction Signing","id":"transaction_signing"},{"title":"Durable Transaction Nonces","id":"transaction_nonces"},{"title":"CLI Usage Reference","id":"usage_reference"}],"title":"Command Line"},"__N_SSG":true}